[
  {
    "urlFoto": "",
    "descricao": "",
    "data": ""
  },
  {
    "urlFoto": "https://thumbs.dreamstime.com/b/macho-lion5-6604483.jpg",
    "descricao": "Um majestoso leão africano descansando na savana.",
    "data": "10/05/2023"
  },
  {
    "urlFoto": "https://guiaanimal.net/uploads/content/image/44925/Design_sem_nome__11_.png",
    "descricao": "Um golfinho saltando fora d'água em uma acrobacia impressionante.",
    "data": "17/07/2023"
  },
  {
    "urlFoto": "https://media.istockphoto.com/id/1092166082/pt/foto/giant-panda-bear-eats-bamboo-leaves-in-a-zoo-in-the-ocean-park-in-hong-kong-china.jpg?s=612x612&w=0&k=20&c=jgWqMFVZEJGH1lrc0TmQ2PyUETDuoQEsaIQr67YFbNk=",
    "descricao": "Um panda adorável brincando com um galho de bambu.",
    "data": "02/09/2023"
  },
  {
    "urlFoto": "https://encrypted-tbn0.gstatic.com/images?q=tbn:ANd9GcQEEhBipZ-R4LQj4h9Z_DK7ZenxTO6QLVnOQDEwFU53EZaRlXn3eCHJ4xifxBFoAEOgojQ&usqp=CAU",
    "descricao": "Um pássaro exótico com plumagem vibrante em tons de azul, laranja e amarelo.",
    "data": "30/06/2023"
  },
  {
    "urlFoto": "https://encrypted-tbn0.gstatic.com/images?q=tbn:ANd9GcR8AaOm-5fKTHiSYx7iUFjAFvLNsxCA7weCgA&usqp=CAU",
    "descricao": "Um cachorro feliz correndo em um campo aberto.",
    "data": "11/04/2023"
  },
  {
    "urlFoto": "https://www.petz.com.br/blog/wp-content/uploads/2021/09/a-curiosidade-matou-o-gato-1280x720.jpg",
    "descricao": "Um gato fofo observando algo intrigante.",
    "data": "08/12/2023"
  },
  {
    "urlFoto": "https://g1.globo.com/Noticias/Ciencia/foto/0,,11399136,00.jpg",
    "descricao": "Um elefante bebê.",
    "data": "20/02/2023"
  },
  {
    "urlFoto": "https://mega.ibxk.com.br/2016/07/01/01210702659427.jpg?ims=610x",
    "descricao": "Uma cobra rara com padrões impressionantes.",
    "data": "05/03/2023"
  },
  {
    "urlFoto": "https://t1.gstatic.com/licensed-image?q=tbn:ANd9GcSJpWBGvXGVO-YYvvTgQLVA0iKXFa04O-7igz7YUzIbSgeeMD9nVk4Q3Tu7k0JE9wrI",
    "descricao": "Um urso polar majestoso caminhando sobre o gelo.",
    "data": "14/11/2023"
  },
  {
    "urlFoto": "https://img.freepik.com/fotos-gratis/macaco-rosnando-e-um-macaco-brincalhao-em-um-galho_181624-59510.jpg?w=740&t=st=1691275089~exp=1691275689~hmac=c7dc87c596891527b5422eb64339d5586506bccd336e33e375e072202f13fcc0",
    "descricao": "Um macaco se divertindo em meio à floresta.",
    "data": "19/10/2023"
  }
]
